xyzrequest/__init__.py
xyzrequest-2022.1.dist-info/LICENSE.txt
xyzrequest-2022.1.dist-info/METADATA
xyzrequest-2022.1.dist-info/WHEEL
xyzrequest-2022.1.dist-info/top_level.txt
xyzrequest-2022.1.dist-info/RECORD
