Metadata-Version: 2.1
Name: xyzrequest
Version: 2022.1
Summary: Modules that make the API easy to get
Author: SunnyLi
Author-email: 5327136@qq.com
License: UNKNOWN
Platform: UNKNOWN
Classifier: Programming Language :: Python :: 3
Classifier: License :: OSI Approved :: MIT License
Classifier: Operating System :: OS Independent
Requires-Python: >=3
License-File: LICENSE.txt
Requires-Dist: requests
Requires-Dist: requests-toolbelt
Requires-Dist: urllib3
Requires-Dist: removebg
Requires-Dist: ISS-info
Requires-Dist: pillow
